translation_strings_utility/__init__.py
translation_strings_utility-0.1.3.dist-info/METADATA
translation_strings_utility-0.1.3.dist-info/WHEEL
translation_strings_utility-0.1.3.dist-info/entry_points.txt
translation_strings_utility-0.1.3.dist-info/RECORD
