Metadata-Version: 2.3
Name: translation-strings-utility
Version: 0.1.3
Summary: 
Author: Jacob Valdez
Author-email: jacobfv123@gmail.com
Requires-Python: >=3.12,<4.0
Classifier: Programming Language :: Python :: 3
Classifier: Programming Language :: Python :: 3.12
Classifier: Programming Language :: Python :: 3.13
Requires-Dist: anthropic (>=0.42.0,<0.43.0)
Requires-Dist: typer (>=0.15.1,<0.16.0)
